README.md
setup.cfg
setup.py
rubrik_cdm/__init__.py
rubrik_cdm/api.py
rubrik_cdm/cloud.py
rubrik_cdm/cluster.py
rubrik_cdm/data_management.py
rubrik_cdm/exceptions.py
rubrik_cdm/organization.py
rubrik_cdm/physical.py
rubrik_cdm/rubrik_cdm.py
rubrik_cdm.egg-info/PKG-INFO
rubrik_cdm.egg-info/SOURCES.txt
rubrik_cdm.egg-info/dependency_links.txt
rubrik_cdm.egg-info/requires.txt
rubrik_cdm.egg-info/top_level.txt
rubrik_cdm.egg-info/zip-safe
tests/integration/__init__.py
tests/integration/cluster_test.py
tests/integration/conftest.py
tests/unit/__init__.py
tests/unit/cloud_test.py
tests/unit/cluster_test.py
tests/unit/conftest.py
tests/unit/data_management_test.py
tests/unit/organization_test.py
tests/unit/physical_test.py
tests/unit/rubrik_cdm_test.py