Metadata-Version: 2.1
Name: rubrik-cdm
Version: 2.0.10
Summary: A Python package for interacting with the Rubrik CDM API.
Home-page: https://github.com/rubrik-devops/rubrik-sdk-for-python
Author: Rubrik Build
License: UNKNOWN
Platform: UNKNOWN
Classifier: Intended Audience :: Information Technology
Classifier: Intended Audience :: System Administrators
Classifier: License :: OSI Approved :: Apache Software License
Classifier: Programming Language :: Python
Classifier: Programming Language :: Python :: 2.7
Classifier: Programming Language :: Python :: 3.6
